mab_ranking/__init__.py
mab_ranking/bandits/__init__.py
mab_ranking/bandits/bandits.py
mab_ranking/bandits/rank_bandits.py
tests/__init__.py
tests/bandits/__init__.py
tests/bandits/test_bandits.py
tests/bandits/test_rank_bandits.py
mab_ranking-0.0.1.dist-info/LICENSE
mab_ranking-0.0.1.dist-info/METADATA
mab_ranking-0.0.1.dist-info/WHEEL
mab_ranking-0.0.1.dist-info/top_level.txt
mab_ranking-0.0.1.dist-info/zip-safe
mab_ranking-0.0.1.dist-info/RECORD
