Metadata-Version: 2.1
Name: mab-ranking
Version: 0.0.1
Summary: Online Ranking with Multi-Armed-Bandits
Home-page: https://github.com/Kenza-AI/mab-ranking
Author: Pavlos Mitsoulis Ntompos, Ioakeim (Joakim) Lazakis
Author-email: pavlos@kenza.ai, joakim@kenza.ai
License: MIT
Keywords: mab-ranking machine-learning machine-learning-deploy machine-learning-production multi-armed-bandits ranking online-ranking multi-armed-bandits-production
Platform: UNKNOWN
Classifier: Development Status :: 5 - Production/Stable
Classifier: License :: OSI Approved :: MIT License
Classifier: Intended Audience :: Developers
Classifier: Intended Audience :: Science/Research
Classifier: Natural Language :: English
Classifier: Programming Language :: Python :: 3
Classifier: Programming Language :: Python :: 3.6
Classifier: Programming Language :: Python :: 3.7
Classifier: Programming Language :: Python :: 3.8
Classifier: Topic :: Scientific/Engineering
Classifier: Topic :: Scientific/Engineering :: Artificial Intelligence
Classifier: Environment :: Console
Requires-Python: ~=3.5
Requires-Dist: boto3
Requires-Dist: paramiko (<2.4.99,>=2.4.2)
Requires-Dist: pathlib2 (<2.3.99,>=2.3.0)
Requires-Dist: requests (<2.20.99,>=2.20.0)
Requires-Dist: sagemaker (<1.50.99,>=1.50.0)
Requires-Dist: six (<1.11.99,>=1.10)
Requires-Dist: future (<0.17.99,>=0.16.0)
